pistream/__init__.py
pistream/Client.py
pistream/Consts.py
pistream/Network.py
pistream/Protocol.py
pistream/Server.py
pistream-1.1.0.2.dist-info/LICENSE
pistream-1.1.0.2.dist-info/METADATA
pistream-1.1.0.2.dist-info/WHEEL
pistream-1.1.0.2.dist-info/RECORD
