Metadata-Version: 2.1
Name: pistream
Version: 1.1.0.2
Summary: Raspberry Pi camera streaming over WIFI for drone photography
License: MIT
Author: Ian Oliva
Requires-Python: >=3.11,<4.0
Classifier: License :: OSI Approved :: MIT License
Classifier: Programming Language :: Python :: 3
Classifier: Programming Language :: Python :: 3.11
Classifier: Programming Language :: Python :: 3.12
Requires-Dist: numpy (>=1.20.0,<2.0.0)
Requires-Dist: opencv-python (>=4.7.0.0,<5.0.0.0)
